[{"title": "Đấu vật biểu diễn WWE RAW | BLV A NÚI | 29.04.25", "logo": "https://g7w1r.4shares.live/images/20250429-WWE-RAW.jpg", "stream": "https://hl.eztool.xyz/hls/2light/thethao/wwe/wwe29425.mp4/playlist.m3u8", "id": "L9L9NvU"}, {"title": "Boxing London Chris Eubank Jr. vs. Conor Benn | BLV A NÚI | 27.04.25", "logo": "https://g7w1r.4shares.live/images/20250427-Boxing.jpg", "stream": "https://hl.eztool.xyz/hls/2light/thethao/wwe/boxing27425.mp4/playlist.m3u8", "id": "MhjzEwZ"}, {"title": "Đấu vật biểu diễn WWE  SMACKDOWN | BLV A NÚI | 26.04.25", "logo": "https://g7w1r.4shares.live/images/20250427-WWE-Smackdown.jpg", "stream": "https://hl.eztool.xyz/hls/2light/thethao/wwe/wwe26425.mp4/playlist.m3u8", "id": "Bp49prQ"}, {"title": "Đấu vật biểu diễn WWE NXT | BLV TAI LUNG | 23.4.25", "logo": "https://g7w1r.4shares.live/images/20250423-WWE-NXT.jpg", "stream": "https://hl.eztool.xyz/hls/2light/thethao/wwe/wwe23425.mp4/playlist.m3u8", "id": "5cGnE22"}, {"title": "Đấu vật biểu diễn WWE RAW | BLV NGƯỜI HÓI | 22.04.25", "logo": "https://g7w1r.4shares.live/images/20250422-WWE-RAW%20(3).jpg", "stream": "https://hl.eztool.xyz/hls/2light/thethao/wwe/wwe22425.mp4/playlist.m3u8", "id": "7PU1xiZ"}, {"title": "Đấu vật biểu diễn WWE Wrestlemania 41  | BLV Người Hói ft Người Cát | 21.04.25", "logo": "https://g7w1r.4shares.live/news/wwe210425.jpg", "stream": "https://hl.eztool.xyz/hls/2light/thethao/wwe/wm night 2.mp4/playlist.m3u8", "id": "BPqqSqQ"}, {"title": "Đấu vật biểu diễn WWE Wrestlemania 41 | BLV A NÚI + TAI LUNG | 20.04.25", "logo": "https://g7w1r.4shares.live/images/20250420-WM41%20(2).jpg", "stream": "https://hl.eztool.xyz/hls/2light/thethao/wwe/wwe20425nuilung.mp4/playlist.m3u8", "id": "b1205Kk"}, {"title": "Đấu vật biểu diễn WWE  Stand & Deliver 2025 | BLV A NÚI | 20.04.25", "logo": "https://g7w1r.4shares.live/images/20250420-NXT%20(2).jpg", "stream": "https://hl.eztool.xyz/hls/2light/thethao/wwe/wwe200425-0000.mp4/playlist.m3u8", "id": "dnlvxmO"}, {"title": "Đấu vật biểu diễn WWE SMACKDOWN | BLV TAI LUNG | 19.4.25", "logo": "https://g7w1r.4shares.live/images/20250419-WWE-Smackdown%20(2).jpg", "stream": "https://hl.eztool.xyz/hls/2light/thethao/wwe/wwelung19425.mp4/playlist.m3u8", "id": "y172aos"}, {"title": "Đấu vật biểu diễn WWE Hall of Fame Ceremony 2025 | BLV NGƯỜI HÓI | 19.4.25", "logo": "https://g7w1r.4shares.live/images/20250419-HoF%20(2).jpg", "stream": "https://hl.eztool.xyz/hls/2light/thethao/wwe/wwe19424.mp4/playlist.m3u8", "id": "fghRwjN"}, {"title": "ONE Friday Fights 104 | BLV NGƯỜI CAST | 19.04.25", "logo": "https://g7w1r.4shares.live/images/20250418-ONE%20(2).jpg", "stream": "https://hl.eztool.xyz/hls/2light/thethao/wwe/ufc19425.mp4/playlist.m3u8", "id": "ceZ0HcL"}, {"title": "Đấu vật biểu diễn WWE NXT | BLV NGƯỜI HÓI | 16.04.25", "logo": "https://g7w1r.4shares.live/images/20250416-WWE-NXT%20(2).jpg", "stream": "https://hl.eztool.xyz/hls/2light/thethao/wwe/wwe16425.mp4/playlist.m3u8", "id": "KbZPGsg"}, {"title": "Đấu vật biểu diễn WWE RAW | BLV A NÚI | 15.04.25", "logo": "https://g7w1r.4shares.live/images/20250415-WWE-RAW.jpg", "stream": "https://hl.eztool.xyz/hls/2light/thethao/wwe/wwenxt15425.mp4/playlist.m3u8", "id": "PfZw4LY"}, {"title": "UFC 314 Alexander Volkanovski vs Diego Lopes | BLV A NÚI | 13.04.25", "logo": "https://g7w1r.4shares.live/images/20250413-UFC.jpg", "stream": "https://hl.eztool.xyz/hls/2light/thethao/wwe/ufc13425.mp4/playlist.m3u8", "id": "4KPxk86"}, {"title": "Đấu vật biểu diễn WWE SMACKDOWN | BLV TAI LUNG | 12.04.25", "logo": "https://g7w1r.4shares.live/images/20250412-WWE-Smackdown.jpg", "stream": "https://hl.eztool.xyz/hls/2light/thethao/wwe/wwe12425.mp4/playlist.m3u8", "id": "A8GSgXF"}, {"title": "Đấu vật biểu diễn WWE NTX | BLV A NÚI | 10.04.25", "logo": "https://g7w1r.4shares.live/images/20250409-WWE-NXT.jpg", "stream": "https://hl.eztool.xyz/hls/2light/thethao/wwe/wwe9425.mp4/playlist.m3u8", "id": "4se0HK0"}, {"title": "One Fight Night 30 : Kryklia vs Knowles | BLV Người Nện | 05.04.25", "logo": "https://g7w1r.4shares.live/images/20250405-ONE%20(2).jpg", "stream": "https://hl.eztool.xyz/hls/2light/thethao/wwe/ufc6425.mp4/playlist.m3u8", "id": "1FLbfGO"}, {"title": "Ufc Fight Night Josh Emmett vs Lerone Murphy | BLV A NÚI | 06.04.25", "logo": "https://g7w1r.4shares.live/images/20250406-UFC.jpg", "stream": "https://hl.eztool.xyz/hls/2light/thethao/wwe/ufc060425.mp4/playlist.m3u8", "id": "Y2mb9yS"}, {"title": "ONE Friday Fights 103 | BLV NGƯỜI CAST | 05.04.25", "logo": "https://g7w1r.4shares.live/images/20250404-ONE%20(2).jpg", "stream": "https://hl.eztool.xyz/hls/2light/thethao/wwe/ufc5425.mp4/playlist.m3u8", "id": "OybEYNo"}, {"title": "Đấu vật biểu diễn WWE SMACKDOWN | BLV A NÚI | 5.4.25", "logo": "https://g7w1r.4shares.live/images/20250405-WWE-Smackdown.jpg", "stream": "https://hl.eztool.xyz/hls/2light/thethao/wwe/wwe4525.mp4/playlist.m3u8", "id": "DYsYuLY"}, {"title": "Đấu vật biểu diễn WWE NXT | BLV TAI LUNG | 2.4.25", "logo": "https://g7w1r.4shares.live/images/20250402-WWE-NXT.jpg", "stream": "https://hl.eztool.xyz/hls/2light/thethao/wwe/wwe-2425.mp4/playlist.m3u8", "id": "YlUvej6"}, {"title": "Đấu vật biểu diễn WWE RAW | BLV NGƯỜI HÓI | 01.04.25", "logo": "https://g7w1r.4shares.live/images/20250401-WWE-RAW.jpg", "stream": "https://hl.eztool.xyz/hls/2light/thethao/wwe/WWE4125.mp4/playlist.m3u8", "id": "LFwldrV"}, {"title": "WBO welterweight world championship  | BLV A NÚI | 30.3.25", "logo": "https://g7w1r.4shares.live/images/20250330-Boxing%20(2).jpg", "stream": "https://hl.eztool.xyz/hls/2light/thethao/wwe/boxing-3003.mp4/playlist.m3u8", "id": "ObqwFGb"}, {"title": "Đấu vật biểu diễn WWE SMACKDOWN  | BLV A NÚI | 29.3.25", "logo": "https://g7w1r.4shares.live/images/20250329-WWE-Smackdown%20(2).jpg", "stream": "https://hl.eztool.xyz/hls/2light/thethao/wwe/wwe-29325.mp4/playlist.m3u8", "id": "tdTwqVC"}, {"title": "Đấu vật biểu diễn WWE NXT | BLV TAI LUNG | 26.3.25", "logo": "https://g7w1r.4shares.live/images/20250326-WWE-NXT%20(2).jpg", "stream": "https://hl.eztool.xyz/hls/2light/thethao/wwe/wwe27325.mp4/playlist.m3u8", "id": "f5SA2tM"}, {"title": "ĐẤU VẬT BIỂU DIỄN WWE RAW | BLV NGƯỜI HÓI | 25.3.25", "logo": "https://g7w1r.4shares.live/news/wwee.jpg", "stream": "https://hl.eztool.xyz/hls/2light/thethao/wwe/wwe-25325.mp4/playlist.m3u8", "id": "wNlBQWd"}, {"title": "ONE Friday Fights 254  | BLV NGƯỜI CAST | 23.03.25", "logo": "https://g7w1r.4shares.live/images/20250323-UFC.jpg", "stream": "https://hl.eztool.xyz/hls/2light/thethao/wwe/ufc23325.mp4/playlist.m3u8", "id": "hip5cDV"}, {"title": "ONE Championship 172: Rodtang vs Takeru | BLV A NÚI | 23.3.25", "logo": "https://g7w1r.4shares.live/images/20250323-ONE.jpg", "stream": "https://hl.eztool.xyz/hls/2light/thethao/wwe/ufc-230325.mp4/playlist.m3u8", "id": "XeE7kE9"}, {"title": "ONE FRIDAY FIGHT 101 | BLV A NÚI | 21.3.25", "logo": "https://g7w1r.4shares.live/images/20250321-ONE%20(2).jpg", "stream": "https://hl.eztool.xyz/hls/2light/thethao/wwe/ufc21325.mp4/playlist.m3u8", "id": "J64YcXw"}, {"title": "Đấu vật biểu diễn WWE NXT | BLV A Núi | 19.3.25", "logo": "https://g7w1r.4shares.live/images/20250319-WWE-NXT.jpg", "stream": "https://hl.eztool.xyz/hls/2light/thethao/wwe/wwe-190325.mp4/playlist.m3u8", "id": "WeeIyxJ"}]